jorm/__init__.py
jorm/conf/__init__.py
jorm/conf/app_template/__init__.py-tpl
jorm/conf/app_template/admin.py-tpl
jorm/conf/app_template/migrations/__init__.py-tpl
jorm/conf/app_template/models.py-tpl
jorm/conf/app_template/tests.py-tpl
jorm/conf/global_settings.py
jorm/conf/project_template/manage.py-tpl
jorm/conf/project_template/project_name/__init__.py-tpl
jorm/conf/project_template/project_name/settings.py-tpl
jorm/core/__init__.py
jorm/core/asgi.py
jorm/core/cache/__init__.py
jorm/core/cache/backends/__init__.py
jorm/core/cache/backends/base.py
jorm/core/cache/backends/db.py
jorm/core/cache/backends/dummy.py
jorm/core/cache/backends/filebased.py
jorm/core/cache/backends/locmem.py
jorm/core/cache/backends/memcached.py
jorm/core/cache/backends/redis.py
jorm/core/cache/utils.py
jorm/core/checks/__init__.py
jorm/core/checks/caches.py
jorm/core/checks/database.py
jorm/core/checks/files.py
jorm/core/checks/messages.py
jorm/core/checks/model_checks.py
jorm/core/checks/registry.py
jorm/core/checks/security/__init__.py
jorm/core/checks/security/base.py
jorm/core/checks/translation.py
jorm/core/exceptions.py
jorm/core/files/__init__.py
jorm/core/files/base.py
jorm/core/files/images.py
jorm/core/files/locks.py
jorm/core/files/move.py
jorm/core/files/storage/__init__.py
jorm/core/files/storage/base.py
jorm/core/files/storage/filesystem.py
jorm/core/files/storage/handler.py
jorm/core/files/storage/memory.py
jorm/core/files/storage/mixins.py
jorm/core/files/temp.py
jorm/core/files/uploadedfile.py
jorm/core/files/uploadhandler.py
jorm/core/files/utils.py
jorm/core/management/__init__.py
jorm/core/management/base.py
jorm/core/management/color.py
jorm/core/management/commands/__init__.py
jorm/core/management/commands/check.py
jorm/core/management/commands/compilemessages.py
jorm/core/management/commands/createcachetable.py
jorm/core/management/commands/dbshell.py
jorm/core/management/commands/diffsettings.py
jorm/core/management/commands/dumpdata.py
jorm-0.1.0.dist-info/LICENSE
jorm-0.1.0.dist-info/METADATA
jorm-0.1.0.dist-info/WHEEL
jorm-0.1.0.dist-info/RECORD
