Metadata-Version: 2.1
Name: jorm
Version: 0.1.0
Summary: Isolated django ORM (as close as possible to official version)
License: MIT
Author: José Luis Escobar Gámez
Author-email: userjleg@gmail.com
Requires-Python: >=3.12,<4.0
Classifier: License :: OSI Approved :: MIT License
Classifier: Programming Language :: Python :: 3
Classifier: Programming Language :: Python :: 3.12
Requires-Dist: asgiref (>=3.7.2,<4.0.0)
